mcu/__init__.py
mcu/main.py
multi_cloud_utils-0.1.0.dist-info/LICENSE
multi_cloud_utils-0.1.0.dist-info/METADATA
multi_cloud_utils-0.1.0.dist-info/WHEEL
multi_cloud_utils-0.1.0.dist-info/entry_points.txt
multi_cloud_utils-0.1.0.dist-info/RECORD
